bootstrappable_cloud9/__init__.py
bootstrappable_cloud9/py.typed
bootstrappable_cloud9/_jsii/__init__.py
bootstrappable_cloud9/_jsii/bootstrappable-cloud9@0.0.5.jsii.tgz
bootstrappable_cloud9-0.0.5.dist-info/LICENSE
bootstrappable_cloud9-0.0.5.dist-info/METADATA
bootstrappable_cloud9-0.0.5.dist-info/WHEEL
bootstrappable_cloud9-0.0.5.dist-info/top_level.txt
bootstrappable_cloud9-0.0.5.dist-info/RECORD
