Metadata-Version: 2.1
Name: bootstrappable-cloud9
Version: 0.0.5
Summary: bootstrappable-cloud9
Home-page: https://github.com/rafams/bootstrappable-cloud9.git
Author: Rafael Mosca<rafams@amazon.es>
License: MIT
Project-URL: Source, https://github.com/rafams/bootstrappable-cloud9.git
Classifier: Intended Audience :: Developers
Classifier: Operating System :: OS Independent
Classifier: Programming Language :: JavaScript
Classifier: Programming Language :: Python :: 3 :: Only
Classifier: Programming Language :: Python :: 3.7
Classifier: Programming Language :: Python :: 3.8
Classifier: Programming Language :: Python :: 3.9
Classifier: Programming Language :: Python :: 3.10
Classifier: Programming Language :: Python :: 3.11
Classifier: Typing :: Typed
Classifier: Development Status :: 5 - Production/Stable
Classifier: License :: OSI Approved
Requires-Python: ~=3.7
License-File: LICENSE
Requires-Dist: aws-cdk-lib <3.0.0,>=2.92.0
Requires-Dist: constructs <11.0.0,>=10.0.5
Requires-Dist: jsii <2.0.0,>=1.87.0
Requires-Dist: publication >=0.0.3
Requires-Dist: typeguard ~=2.13.3
